neural_dream/__init__.py
neural_dream/neural_dream.py
neural_dream/neural_dream_core/CaffeLoader.py
neural_dream/neural_dream_core/__init__.py
neural_dream/neural_dream_core/dream_auto.py
neural_dream/neural_dream_core/dream_experimental.py
neural_dream/neural_dream_core/dream_image.py
neural_dream/neural_dream_core/dream_model.py
neural_dream/neural_dream_core/dream_tile.py
neural_dream/neural_dream_core/dream_utils.py
neural_dream/neural_dream_core/helper_layers.py
neural_dream/neural_dream_core/loss_layers.py
neural_dream/neural_dream_core/models/__init__.py
neural_dream/neural_dream_core/models/googlenet/__init__.py
neural_dream/neural_dream_core/models/googlenet/bvlc_googlenet.py
neural_dream/neural_dream_core/models/googlenet/googlenet_cars.py
neural_dream/neural_dream_core/models/googlenet/googlenet_layer_names.py
neural_dream/neural_dream_core/models/googlenet/googlenet_sos.py
neural_dream/neural_dream_core/models/googlenet/googlenetplaces.py
neural_dream/neural_dream_core/models/inception/__init__.py
neural_dream/neural_dream_core/models/inception/inception5h.py
neural_dream/neural_dream_core/models/inception/inception_layer_names.py
neural_dream/neural_dream_core/models/inception/inceptionv3_keras.py
neural_dream/neural_dream_core/models/resnet/__init__.py
neural_dream/neural_dream_core/models/resnet/resnet_50_1by2_nsfw.py
neural_dream/neural_dream_core/models/resnet/resnet_layer_names.py
neural_dream-0.0.4.dist-info/LICENSE
neural_dream-0.0.4.dist-info/METADATA
neural_dream-0.0.4.dist-info/WHEEL
neural_dream-0.0.4.dist-info/entry_points.txt
neural_dream-0.0.4.dist-info/top_level.txt
neural_dream-0.0.4.dist-info/RECORD
