Metadata-Version: 2.1
Name: neural-dream
Version: 0.0.4
Summary: A PyTorch implementation of DeepDream
Home-page: https://github.com/ProGamerGov/neural-dream/tree/pip-master/
Author: ProGamerGov
License: UNKNOWN
Keywords: neural artistic neural-dream dream pytorch caffe neuralart neural-art hallucinations visualization feature-visualization mlart machine-learning-art aiart ai-art deepdream neuraldream pytorch-deepdream deepdream-pytorch tiling googlenet inception resnet vgg vgg16 vgg19 nin tensorflow keras inceptionv3 inception-v3
Platform: UNKNOWN
Classifier: Development Status :: 5 - Production/Stable
Classifier: Intended Audience :: Science/Research
Classifier: Intended Audience :: End Users/Desktop
Classifier: Topic :: Artistic Software
Classifier: Topic :: Scientific/Engineering :: Artificial Intelligence
Classifier: Programming Language :: Python :: 2
Classifier: Programming Language :: Python :: 3
Classifier: License :: OSI Approved :: MIT License
Classifier: Operating System :: OS Independent
Requires-Dist: torch
Requires-Dist: torchvision
Requires-Dist: pillow
